coriander/__init__.py
coriander-0.2.0.dist-info/WHEEL
coriander-0.2.0.dist-info/METADATA
coriander-0.2.0.dist-info/RECORD
