Metadata-Version: 2.1
Name: coriander
Version: 0.2.0
Summary: A simple library for intent classification and named-entity recognition using templates.
Home-page: https://github.com/odryfox/coriander
Author: Vyacheslav Rusov
Author-email: odryfox@gmail.com
